LICENSE
README.md
oko/__init__.py
oko/main.py
oko/commands/__init__.py
oko/commands/collection_cmd.py
oko/commands/endpoint_cmd.py
oko/commands/init_cmd.py
oko/commands/variable_cmd.py
oko/service/__init__.py
oko/service/service_collection.py
oko/service/service_config.py
oko/service/service_endpoint.py
oko/service/service_variable.py
oko/ui/__init__.py
oko/ui/formatters.py
oko/ui/logo.py
oko/ui/prints.py
oko/ui/theme.py
oko_cli-0.2.1.dist-info/METADATA
oko_cli-0.2.1.dist-info/WHEEL
oko_cli-0.2.1.dist-info/entry_points.txt
oko_cli-0.2.1.dist-info/licenses/LICENSE
oko_cli-0.2.1.dist-info/RECORD
