Metadata-Version: 2.4
Name: oko-cli
Version: 0.2.1
Summary: Elegant CLI for API endpoint testing
Project-URL: Homepage, https://github.com/poll7872/oko
Project-URL: Repository, https://github.com/tuusuario/oko
Project-URL: Issues, https://github.com/poll7872/oko/issues
Author-email: Edward Ojeda <edward.ojeda.es@gmail.com>
License: MIT
License-File: LICENSE
Keywords: api,cli,endpoints,http,rest,testing
Classifier: Development Status :: 4 - Beta
Classifier: Intended Audience :: Developers
Classifier: License :: OSI Approved :: MIT License
Classifier: Programming Language :: Python :: 3
Classifier: Programming Language :: Python :: 3.8
Classifier: Programming Language :: Python :: 3.9
Classifier: Programming Language :: Python :: 3.10
Classifier: Programming Language :: Python :: 3.11
Classifier: Programming Language :: Python :: 3.12
Classifier: Programming Language :: Python :: 3.13
Classifier: Topic :: Software Development :: Testing
Requires-Python: >=3.8
Requires-Dist: httpx>=0.25.0
Requires-Dist: rich>=13.0.0
Requires-Dist: typer>=0.9.0
